waps/__init__.py
waps/waps.py
waps-1.0.2.dist-info/LICENSE.txt
waps-1.0.2.dist-info/METADATA
waps-1.0.2.dist-info/WHEEL
waps-1.0.2.dist-info/top_level.txt
waps-1.0.2.dist-info/RECORD
