Metadata-Version: 2.1
Name: waps
Version: 1.0.2
Summary: This library can be used to sample satisfying assignments for a CNF/DNF obeying a given literal-weighted weight function and projected upon a given sampling set.
Home-page: https://github.com/meelgroup/waps/
Author: Rahul Gupta
Author-email: rahujupiter@gmail.com
License: MIT
Download-URL: https://github.com/meelgroup/waps/archive/v1.0.2.tar.gz
Keywords: sampling,cnf,weighted sampling,projected sampling,dDNNF
Platform: UNKNOWN
Classifier: Development Status :: 3 - Alpha
Classifier: Intended Audience :: Developers
Classifier: Topic :: Software Development :: Build Tools
Classifier: License :: OSI Approved :: MIT License
Classifier: Programming Language :: Python :: 3
Classifier: Programming Language :: Python :: 3.4
Classifier: Programming Language :: Python :: 3.5
Classifier: Programming Language :: Python :: 3.6
Classifier: Programming Language :: Python :: 3.7
